{"web":{"client_id":"159773738685-0u9jpcjp3pj1ms0k30s5jpuvgabiisvq.apps.googleusercontent.com","project_id":"project-id-9411337968201629460","auth_uri":"https://accounts.google.com/o/oauth2/auth","token_uri":"https://www.googleapis.com/oauth2/v3/token","auth_provider_x509_cert_url":"https://www.googleapis.com/oauth2/v1/certs","client_secret":"ytV_BuAEaIGSIJgRYLD-DjXF","redirect_uris":["http://localhost/biz/wf_gaisan_syusei/oauth2_callback","http://admonster-test.adpro-inc.co.jp/biz/wf_gaisan_syusei/oauth2_callback"]}}